LICENSE
README.md
pyproject.toml
setup.py
src/downloadutil/__init__.py
src/downloadutil/__main__.py
src/downloadutil/checksum_util.py
src/downloadutil/download_cache.py
src/downloadutil/download_config.py
src/downloadutil/download_strategy.py
src/downloadutil/download_util.py
src/downloadutil/downloader.py
src/downloadutil/util.py
src/downloadutil.egg-info/PKG-INFO
src/downloadutil.egg-info/SOURCES.txt
src/downloadutil.egg-info/dependency_links.txt
src/downloadutil.egg-info/entry_points.txt
src/downloadutil.egg-info/requires.txt
src/downloadutil.egg-info/top_level.txt