Metadata-Version: 2.1
Name: downloadutil
Version: 1.0.4
Summary: Common utilities for downloading and extracting archives
Home-page: https://github.com/yugabyte/downloadutil
Author: Mikhail Bautin
Author-email: mbautin@users.noreply.github.com
Classifier: Programming Language :: Python :: 3
Classifier: License :: OSI Approved :: Apache Software License
Classifier: Operating System :: OS Independent
Requires-Python: >=3.6
Provides-Extra: dev
License-File: LICENSE
